{
	"title": "hidden",
	"videos": {
		"aborigeno": {
			"title": "Aborigeno, ma io e te che cazzo se dovemo dì? (Guzzanti)",
			"url": "https://www.youtube.com/watch?v=igBDa6a0NmE"
		},
		"buongiorno-una-sega": {
			"title": "Buongiorno una sega (Nuti)",
			"url": "https://www.youtube.com/watch?v=_AtOyXEEyxE"
		},
		"cafonata": {
			"title": "Ma che è sta cafonata?",
			"url": "https://www.youtube.com/watch?v=G_SldLRtsN0"
		},
		"capra": {
			"title": "Capra! (Sgarbi)",
			"url": "https://www.youtube.com/watch?v=QSwnN8d9TG8"
		},
		"ed-ora": {
			"title": "Ed ora andate - Marcilo Agro e il Duo Maravilha",
			"url": "https://www.youtube.com/watch?v=WWmQSOojvOg"
		},
		"fascio": {
			"title": "A me fascio? Io non son comunista così... (Verdone + Mario Brega)",
			"url": "https://www.youtube.com/watch?v=IPlYNw-L2Dc"
		},
		"fodera": {
			"title": "M'hai rotto la fodera del cazzo (Tomas Milian)",
			"url": "https://www.youtube.com/watch?v=BATADXOoO2w"
		},
		"giorno-sbagliato": {
			"title": "Ho scelto il giorno sbagliato per smettere di fumare",
			"url": "https://www.youtube.com/watch?v=yhvuiWrevpE"
		},
		"hai-rotto-il-cazzo": {
			"title": "Hai rotto il cazzo (Guzzanti)",
			"url": "https://www.youtube.com/watch?v=Qcr0XCBw9ug"
		},
		"ignorante": {
			"title": "Lei è ignorante come una capra (Sgarbi)",
			"url": "https://www.youtube.com/watch?v=936gPA5gnJg"
		},
		"in-che-senso": {
			"title": "In che senso? (Verdone)",
			"url": "https://www.youtube.com/watch?v=r-kvBwmxU-I"
		},
		"io-so-io": {
			"title": "Io so io, e voi non siete un cazzo (Alberto Sordi)",
			"url": "https://www.youtube.com/watch?v=kN9VK9IXj10"
		},
		"lavoro-schifoso": {
			"title": "Potrebbe andare peggio, potrebbe piovere",
			"url": "https://www.youtube.com/watch?v=olKKWG3HwOg"
		},
		"minchia": {
			"title": "Minchia!",
			"url": "https://www.youtube.com/watch?v=SjNl7BpnWFU"
		},
		"morire": {
			"title": "Ricordati che devi morire. Mo' me lo segno (Troisi)",
			"url": "https://www.youtube.com/watch?v=eBP9QDSr0HI"
		},
		"nessuno": {
			"title": "C'è nessuno? (particella di sodio)",
			"url": "https://www.youtube.com/watch?v=x2EruMTGbiU"
		},
		"non-me-ne-frega": {
			"title": "Non me ne frega un cazzo (Nino Manfredi)",
			"url": "https://www.youtube.com/watch?v=-MIKLeXtI1o"
		},
		"occasione": {
			"title": "Era tanto che aspettavo un'occasione così (Jerry Calà)",
			"url": "https://www.youtube.com/watch?v=IGJ09FMOPqo"
		},
		"stronzoli": {
			"title": "Stronzoli nel culo (Benigni)",
			"url": "https://www.youtube.com/watch?v=HukL-nhfL9E"
		},
		"taci": {
			"title": "Taci (Sgarbi)",
			"url": "https://www.youtube.com/watch?v=AmFt4z2pSJQ"
		}
	}
}